{"first_downs": {"total": 21, "passing": 9, "rushing": 9, "from_penalties": 3, "third_down_efficiency": "3-10", "fourth_down_efficiency": "1-1"}, "plays": {"total": 60}, "yards": {"total": 326, "yards_per_play": "10", "total_drives": "5.4"}, "passing": {"total": 189, "comp_att": "20-29", "yards_per_pass": "6.1", "interceptions_thrown": 0, "sacks_yards_lost": "2-15"}, "rushings": {"total": 137, "attempts": 29, "yards_per_rush": "4.7"}, "red_zone": {"made_att": "3-4"}, "penalties": {"total": "4-20"}, "turnovers": {"total": 0, "lost_fumbles": 0, "interceptions": 0}, "posession": {"total": "30:58"}, "interceptions": {"total": 3}, "fumbles_recovered": {"total": 0}, "sacks": {"total": 0}, "safeties": {"total": 0}, "int_touchdowns": {"total": 2}, "points_against": {"total": 34}}